bitrix24/__init__.py
bitrix24/bitrix24.py
bitrix24/exceptions.py
tests/__init__.py
tests/test_bitrix24.py
bitrix24_rest_motexc-1.1.5.dist-info/LICENSE
bitrix24_rest_motexc-1.1.5.dist-info/METADATA
bitrix24_rest_motexc-1.1.5.dist-info/WHEEL
bitrix24_rest_motexc-1.1.5.dist-info/top_level.txt
bitrix24_rest_motexc-1.1.5.dist-info/RECORD
