Metadata-Version: 2.1
Name: bitrix24-rest-motexc
Version: 1.1.5
Summary: A fork of bitrix24-rest package, abandoned by it's author Akop Kesheshyan
Home-page: https://github.com/Motexc/bitrix24-python-rest.git
Author: Andrey Yakovlev
Author-email: modifikator97@gmail.com
License: MIT
Keywords: bitrix24 api rest fork
Classifier: Development Status :: 4 - Beta
Classifier: Intended Audience :: Developers
Classifier: Natural Language :: Russian
Classifier: Natural Language :: English
Classifier: Operating System :: OS Independent
Classifier: Topic :: Software Development :: Libraries :: Python Modules
Classifier: License :: OSI Approved :: MIT License
Classifier: Programming Language :: Python :: 3
License-File: LICENSE
Requires-Dist: requests
